blackjax/__init__.py
blackjax/_version.py
blackjax/base.py
blackjax/diagnostics.py
blackjax/progress_bar.py
blackjax/types.py
blackjax/util.py
blackjax/adaptation/__init__.py
blackjax/adaptation/adjusted_mclmc_adaptation.py
blackjax/adaptation/base.py
blackjax/adaptation/chees_adaptation.py
blackjax/adaptation/mass_matrix.py
blackjax/adaptation/mclmc_adaptation.py
blackjax/adaptation/meads_adaptation.py
blackjax/adaptation/pathfinder_adaptation.py
blackjax/adaptation/step_size.py
blackjax/adaptation/window_adaptation.py
blackjax/mcmc/__init__.py
blackjax/mcmc/adjusted_mclmc.py
blackjax/mcmc/adjusted_mclmc_dynamic.py
blackjax/mcmc/barker.py
blackjax/mcmc/diffusions.py
blackjax/mcmc/dynamic_hmc.py
blackjax/mcmc/elliptical_slice.py
blackjax/mcmc/ghmc.py
blackjax/mcmc/hmc.py
blackjax/mcmc/integrators.py
blackjax/mcmc/mala.py
blackjax/mcmc/marginal_latent_gaussian.py
blackjax/mcmc/mclmc.py
blackjax/mcmc/metrics.py
blackjax/mcmc/nuts.py
blackjax/mcmc/periodic_orbital.py
blackjax/mcmc/proposal.py
blackjax/mcmc/random_walk.py
blackjax/mcmc/rmhmc.py
blackjax/mcmc/termination.py
blackjax/mcmc/trajectory.py
blackjax/optimizers/__init__.py
blackjax/optimizers/dual_averaging.py
blackjax/optimizers/lbfgs.py
blackjax/sgmcmc/__init__.py
blackjax/sgmcmc/csgld.py
blackjax/sgmcmc/diffusions.py
blackjax/sgmcmc/gradients.py
blackjax/sgmcmc/sghmc.py
blackjax/sgmcmc/sgld.py
blackjax/sgmcmc/sgnht.py
blackjax/smc/__init__.py
blackjax/smc/adaptive_persistent_sampling.py
blackjax/smc/adaptive_tempered.py
blackjax/smc/base.py
blackjax/smc/ess.py
blackjax/smc/from_mcmc.py
blackjax/smc/inner_kernel_tuning.py
blackjax/smc/partial_posteriors_path.py
blackjax/smc/persistent_sampling.py
blackjax/smc/pretuning.py
blackjax/smc/resampling.py
blackjax/smc/solver.py
blackjax/smc/tempered.py
blackjax/smc/waste_free.py
blackjax/smc/tuning/__init__.py
blackjax/smc/tuning/from_kernel_info.py
blackjax/smc/tuning/from_particles.py
blackjax/vi/__init__.py
blackjax/vi/meanfield_vi.py
blackjax/vi/pathfinder.py
blackjax-1.3.dist-info/licenses/LICENSE
blackjax-1.3.dist-info/METADATA
blackjax-1.3.dist-info/WHEEL
blackjax-1.3.dist-info/top_level.txt
blackjax-1.3.dist-info/RECORD
