Metadata-Version: 2.4
Name: blackjax
Version: 1.3
Summary: Flexible and fast sampling in Python
Author-email: The Blackjax team <remi@thetypicalset.com>
License: Apache License 2.0
Project-URL: homepage, https://github.com/blackjax-devs/blackjax
Project-URL: documentation, https://blackjax-devs.github.io/blackjax/
Project-URL: repository, https://github.com/blackjax-devs/blackjax
Keywords: probability,machine learning,statistics,mcmc,sampling
Platform: Linux
Platform: Mac OS-X
Platform: Unix
Classifier: Development Status :: 5 - Production/Stable
Classifier: Intended Audience :: Developers
Classifier: Intended Audience :: Information Technology
Classifier: Intended Audience :: Science/Research
Classifier: License :: OSI Approved :: Apache Software License
Classifier: Operating System :: MacOS
Classifier: Operating System :: POSIX
Classifier: Programming Language :: Python :: 3.9
Classifier: Programming Language :: Python :: 3.12
Classifier: Programming Language :: Python :: 3.12
Classifier: Topic :: Education
Classifier: Topic :: Scientific/Engineering
Classifier: Topic :: Scientific/Engineering :: Artificial Intelligence
Classifier: Topic :: Scientific/Engineering :: Mathematics
Requires-Python: >=3.9
License-File: LICENSE
Requires-Dist: fastprogress>=1.0.0
Requires-Dist: jax>=0.4.16
Requires-Dist: jaxlib>=0.4.16
Requires-Dist: jaxopt<=0.8.3
Requires-Dist: optax>=0.1.7
Requires-Dist: typing-extensions>=4.4.0
Dynamic: license-file
